cache/__init__.py
cache/flush.py
cache/sync.py
helix_p4p_cache-0.0.1.dist-info/LICENSE
helix_p4p_cache-0.0.1.dist-info/METADATA
helix_p4p_cache-0.0.1.dist-info/WHEEL
helix_p4p_cache-0.0.1.dist-info/entry_points.txt
helix_p4p_cache-0.0.1.dist-info/top_level.txt
helix_p4p_cache-0.0.1.dist-info/RECORD
