Metadata-Version: 2.1
Name: helix-p4p-cache
Version: 0.0.1
Summary: Helix P4P caching extensions
Home-page: https://packages.python.org/helix-p4p-cache
Author: Peter Brooks
Author-email: Peter Brooks <commit@neonspark.io>
License: MIT
Project-URL: Homepage, https://github.com/pbrooks/helix-p4p-cache
Project-URL: Bug Tracker, https://github.com/pbrooks/helix-p4p-cache/issues
Keywords: perforce proxy cache
Classifier: Programming Language :: Python :: 3
Classifier: Development Status :: 3 - Alpha
Classifier: License :: OSI Approved :: MIT License
Requires-Python: >=3.7
License-File: LICENSE
